{
  "version": 1,
  "readingJourney": {
    "cover": {
      "contentType": "image/jpeg",
      "url": "https://img1.od-cdn.com/ImageType-100/1493-1/{63A9D0DE-86BB-48BC-A803-4CCC308DB173}Img100.jpg",
      "title": "Mind Games",
      "color": "#645E80",
      "format": "audiobook"
    },
    "title": {
      "text": "Mind Games",
      "url": "https://share.libbyapp.com/title/4300835",
      "titleId": "4300835"
    },
    "author": "Shana Silver",
    "publisher": "Macmillan Audio",
    "isbn": "9781250211989",
    "percent": 0.188653067915294
  },
  "bookmarks": [
    {
      "timestamp": 1688112963000,
      "percent": 0.17510042135203,
      "note": "So she’s probably in middle school or high school. She’s still too immature to realize that the hacker is only removing memories related to her school project (as a devil’s advocate, however, it is her life that’s being toyed with. And so panic sets in and you can’t think clearly)"
    },
    {
      "timestamp": 1687839631000,
      "percent": 0.172200310610205,
      "note": "Ducking A, just back them up already…\nFinally"
    },
    {
      "timestamp": 1687838502000,
      "percent": 0.151037753349736,
      "note": "She clearly doesn’t know videos. 1007 MB vs. 400 kB. You can’t have any space in a couple-kilobyte file"
    },
    {
      "timestamp": 1687533993000,
      "percent": 0.134615607788854,
      "note": "Why would he write it down? Oh, because he already knew that he had lost his memories by the time he left the house, so he was writing it down so he wouldn't forget"
    },
    {
      "timestamp": 1687476023000,
      "percent": 0.0990724965449683,
      "note": "# lesson call late now, but this would've helped a lot when I was a teen. This quote about her and being is ability to remain calm it's a lesson for guys call M girls want guys to remain calm and S&M varsity. They like the more after that. So if you're trying to sleep with on Mario girl calm a she will like you nor if she sees that you are a man stoic."
    },
    {
      "timestamp": 1687475501000,
      "percent": 0.0933600682878721,
      "note": "In modern day science and business, you can never let other people know that you made a mistake. It's horrible. You always have to conveyor demeanor as though you know and remember everything."
    },
    {
      "timestamp": 1687447174000,
      "percent": 0.0769846127611111,
      "note": "“I search HiveMind for keywords, like, ‘todo,’ ‘project,’ and ‘thesis.’” This is exactly like Obsidian. I wonder if I can invest in Obsidian, because this thing is going to be huge."
    },
    {
      "timestamp": 1687446914000,
      "percent": 0.072578496072041,
      "note": "So I guess the author uses Einstein in every place that modern people use Jesus. To signify that this is a scientific school in the same way that our Society is a religious society"
    },
    {
      "timestamp": 1687425404000,
      "percent": 0.0669005747783223,
      "note": "No, you don’t. It's OK to not be the best; you can still start a business worth billions"
    },
    {
      "timestamp": 1687425229000,
      "percent": 0.0638696896875344,
      "note": "What *are* the phases of cell division (In order, including both mitosis and meiosis)?"
    },
    {
      "timestamp": 1687071477000,
      "percent": 0.0386291370537037,
      "note": "Why “set a delay” for the memory?"
    }
  ],
  "circulation": [
    {
      "timestamp": 1687765035000,
      "activity": "Borrowed",
      "details": " 21 days ",
      "library": {
        "text": "Brooklyn Public Library",
        "url": "https://libbyapp.com/library/brooklyn",
        "key": "brooklyn"
      }
    },
    {
      "timestamp": 1684548594728,
      "activity": "Tagged",
      "details": "🧾",
      "library": {
        "text": "Brooklyn Public Library",
        "url": "https://libbyapp.com/library/brooklyn",
        "key": "brooklyn"
      }
    }
  ]
}